{"version":1,"name":"meeting","rel":"diamondcoreprocessor.com/meeting","bees":["26148d5173340476b472147d01be5faac089ce0620ab61729ffd159c1c8d1f0a.js","7a3b5bfd3c7625bbf71dc5d160513db2f72b990b267890f4f6445a27332f357c.js","b4fe052d64193c3b60fcc2fdec1322074594f3ea50fc21aab48b370a9740b9bd.js","e1dbcb1ef55016c980c426eda538ac9beb8cbb056ce5b9dcd7bb5b1d2724e27b.js"],"dependencies":[],"layers":[],"docs":{"bees":{"26148d5173340476b472147d01be5faac089ce0620ab61729ffd159c1c8d1f0a":{"className":"HiveMeetingDrone","kind":"drone","description":"Orchestrates hive meetings — availability tracking, WebRTC signaling, peer connections.","effects":["network"],"listens":["render:cell-count","mesh:ensure-started","meeting:toggle-camera","meeting:toggle-available"],"emits":["meeting:state","meeting:streams","meeting:local-camera"],"deps":{"mesh":"@diamondcoreprocessor.com/NostrMeshDrone"},"grammar":[],"links":[],"command":null,"aliases":[]},"7a3b5bfd3c7625bbf71dc5d160513db2f72b990b267890f4f6445a27332f357c":{"className":"MeetingControlsWorker","kind":"worker","description":"Registers join/camera overlay buttons for hive meetings.","effects":["network"],"listens":["render:host-ready","tile:action","meeting:state","meeting:local-camera"],"emits":["overlay:register-action","overlay:unregister-action","meeting:toggle-available","meeting:toggle-camera"],"deps":{},"grammar":[],"links":[],"command":null,"aliases":[]},"b4fe052d64193c3b60fcc2fdec1322074594f3ea50fc21aab48b370a9740b9bd":{"className":"MeetingVideoDrone","kind":"drone","description":"Renders peer video streams into hex tiles — hex-clipped, faded in/out on connect/disconnect.","effects":["render"],"listens":["meeting:streams","meeting:state","render:host-ready","render:geometry-changed","render:cell-count"],"emits":[],"deps":{},"grammar":[],"links":[],"command":null,"aliases":[]},"e1dbcb1ef55016c980c426eda538ac9beb8cbb056ce5b9dcd7bb5b1d2724e27b":{"className":"HypercombMeetingDrone","kind":"drone","description":"Enables video meetings on tiles tagged with meeting keywords (e.g. cascade).","effects":[],"listens":["tags:changed","render:host-ready","tile:action"],"emits":["overlay:register-action","meeting:stream-ready","meeting:slot-assigned","mesh:publish","mesh:subscribe"],"deps":{"mesh":"@diamondcoreprocessor.com/NostrMeshDrone"},"grammar":[],"links":[],"command":null,"aliases":[]},"queen:MeetingQueenBee":{"className":"MeetingQueenBee","kind":"queen","description":"Start or join a video meeting on the selected tile","effects":[],"listens":[],"emits":[],"deps":{},"grammar":[],"links":[],"command":"meeting","aliases":[]}}}}